{"positions": [{"x": "5890", "y": "7610"}, {"x": "6514", "y": "7610"}, {"x": "7138", "y": "7610"}, {"x": "7762", "y": "7610"}, {"x": "8386", "y": "7610"}, {"x": "9010", "y": "7610"}, {"x": "9634", "y": "7610"}, {"x": "10258", "y": "7610"}, {"x": "11531", "y": "7610"}, {"x": "12145", "y": "7610"}, {"x": "12759", "y": "7610"}, {"x": "13373", "y": "7610"}, {"x": "13987", "y": "7610"}, {"x": "14601", "y": "7610"}, {"x": "15215", "y": "7610"}, {"x": "16637", "y": "7610"}, {"x": "17261", "y": "7610"}, {"x": "17885", "y": "7610"}, {"x": "18509", "y": "7610"}, {"x": "19133", "y": "7610"}, {"x": "19757", "y": "7610"}, {"x": "20381", "y": "7610"}, {"x": "21005", "y": "7610"}, {"x": "22279", "y": "7610"}, {"x": "22903", "y": "7610"}, {"x": "23527", "y": "7610"}, {"x": "24151", "y": "7610"}, {"x": "24775", "y": "7610"}, {"x": "25398", "y": "7610"}, {"x": "26022", "y": "7610"}, {"x": "26646", "y": "7610"}, {"x": "27920", "y": "7610"}, {"x": "28544", "y": "7610"}, {"x": "29168", "y": "7610"}, {"x": "29792", "y": "7610"}, {"x": "30416", "y": "7610"}, {"x": "31040", "y": "7610"}, {"x": "31664", "y": "7610"}, {"x": "32288", "y": "7610"}, {"x": "3952", "y": "13264"}, {"x": "4616", "y": "13264"}, {"x": "5280", "y": "13264"}, {"x": "5944", "y": "13264"}, {"x": "6608", "y": "13264"}, {"x": "7272", "y": "13264"}, {"x": "7936", "y": "13264"}, {"x": "8600", "y": "13264"}, {"x": "9874", "y": "13264"}, {"x": "10538", "y": "13264"}, {"x": "11202", "y": "13264"}, {"x": "11866", "y": "13264"}, {"x": "12530", "y": "13264"}, {"x": "13194", "y": "13264"}, {"x": "13858", "y": "13264"}, {"x": "14522", "y": "13264"}, {"x": "15796", "y": "13264"}, {"x": "16460", "y": "13264"}, {"x": "17124", "y": "13264"}, {"x": "17788", "y": "13264"}, {"x": "18452", "y": "13264"}, {"x": "19116", "y": "13264"}, {"x": "19780", "y": "13264"}, {"x": "20444", "y": "13264"}, {"x": "21718", "y": "13264"}, {"x": "22382", "y": "13264"}, {"x": "23046", "y": "13264"}, {"x": "23710", "y": "13264"}, {"x": "24374", "y": "13264"}, {"x": "25038", "y": "13264"}, {"x": "25702", "y": "13264"}, {"x": "26366", "y": "13264"}, {"x": "27640", "y": "13264"}, {"x": "28304", "y": "13264"}, {"x": "28968", "y": "13264"}, {"x": "29632", "y": "13264"}, {"x": "30296", "y": "13264"}, {"x": "30960", "y": "13264"}, {"x": "31624", "y": "13264"}, {"x": "32288", "y": "13264"}, {"x": "3952", "y": "18919"}, {"x": "5764", "y": "18919"}, {"x": "7577", "y": "18919"}, {"x": "9389", "y": "18919"}, {"x": "11202", "y": "18919"}, {"x": "13015", "y": "18919"}, {"x": "14827", "y": "18919"}, {"x": "16640", "y": "18919"}, {"x": "18893", "y": "18919"}, {"x": "20730", "y": "18919"}, {"x": "22568", "y": "18919"}, {"x": "24405", "y": "18919"}, {"x": "26243", "y": "18919"}, {"x": "28080", "y": "18919"}, {"x": "29918", "y": "18919"}]}